[{"2022-11-18T12:30:22.263Z":{"minutes":"00","seconds":"19","moves":6}},{"2022-11-18T04:15:41.918Z":{"minutes":"00","seconds":"17","moves":11}},{"2022-11-17T13:14:14.266Z":{"minutes":"01","seconds":"56","moves":87}},{"2022-11-17T13:07:43.994Z":{"minutes":"00","seconds":"10","moves":7}},{"2022-11-17T13:07:07.674Z":{"minutes":"00","seconds":"18","moves":11}},{"2022-11-17T13:06:22.620Z":{"minutes":"00","seconds":"03","moves":3}},{"2022-11-17T13:06:08.505Z":{"minutes":"00","seconds":"07","moves":4}},{"2022-11-17T13:01:57.577Z":{"minutes":"00","seconds":"06","moves":3}},{"2022-11-17T13:00:37.567Z":{"minutes":"00","seconds":"04","moves":2}},{"2022-11-17T12:35:01.593Z":{"minutes":"00","seconds":"23","moves":7}},{"2022-11-17T12:07:35.677Z":{"minutes":"00","seconds":"00","moves":"0"}},{"2022-11-17T12:00:03.378Z":{"minutes":"00","seconds":"20","moves":4}},{"2022-11-17T11:59:31.294Z":{"minutes":"00","seconds":"10","moves":3}},{"2022-11-17T11:59:02.305Z":{"minutes":"00","seconds":"10","moves":8}},{"2022-11-17T10:39:33.767Z":{"minutes":"00","seconds":"02","moves":2}},{"2022-11-17T10:34:17.322Z":{"minutes":"00","seconds":"52","moves":28}},{"2022-11-17T10:02:24.411Z":{"minutes":"00","seconds":"16","moves":37}},{"2022-11-17T08:45:47.587Z":{"minutes":"00","seconds":"05","moves":4}},{"2022-11-17T08:45:26.479Z":{"minutes":"00","seconds":"04","moves":4}},{"2022-11-17T07:45:06.156Z":{"minutes":"00","seconds":"00","moves":"0"}},{"2022-11-17T07:34:37.739Z":{"minutes":"00","seconds":"00","moves":"0"}},{"2022-11-17T07:34:33.173Z":{"minutes":"00","seconds":"24","moves":12}},{"2022-11-17T07:33:58.658Z":{"minutes":"00","seconds":"21","moves":2}},{"2022-11-17T06:45:21.460Z":{"minutes":"00","seconds":"00","moves":"0"}},{"2022-11-17T06:45:15.066Z":{"minutes":"00","seconds":"07","moves":2}},{"2022-11-17T06:45:02.606Z":{"minutes":"00","seconds":"04","moves":2}},{"2022-11-17T04:41:52.182Z":{"minutes":"00","seconds":"15","moves":13}},{"2022-11-17T04:03:29.630Z":{"minutes":"00","seconds":"22","moves":18}},{"2022-11-17T04:02:27.655Z":{"minutes":"00","seconds":"24","moves":18}},{"2022-11-16T12:31:07.848Z":{"minutes":"00","seconds":"21","moves":12}},{"2022-11-16T10:42:34.619Z":{"minutes":"00","seconds":"02","moves":2}},{"2022-11-16T10:40:56.275Z":{"minutes":"00","seconds":"11","moves":3}},{"2022-11-16T10:37:47.137Z":{"minutes":"00","seconds":"13","moves":9}},{"2022-11-16T10:23:51.925Z":{"minutes":"00","seconds":"30","moves":4}},{"2022-11-16T10:20:32.207Z":{"minutes":"00","seconds":"10","moves":6}},{"2022-11-16T10:20:01.374Z":{"minutes":"00","seconds":"07","moves":6}},{"2022-11-16T10:17:15.551Z":{"minutes":"00","seconds":"05","moves":"0"}},{"2022-11-16T09:56:59.846Z":{"minutes":"00","seconds":"06","moves":5}},{"2022-11-16T09:29:00.446Z":{"minutes":"00","seconds":"15","moves":8}},{"2022-11-16T09:18:21.257Z":{"minutes":"00","seconds":"49","moves":34}},{"2022-11-16T09:17:54.272Z":{"minutes":"00","seconds":"48","moves":34}},{"2022-11-16T08:57:11.174Z":{"minutes":"00","seconds":"00","moves":"0"}},{"2022-11-16T08:48:58.338Z":{"minutes":"00","seconds":"07","moves":4}},{"2022-11-16T08:46:28.580Z":{"minutes":"00","seconds":"07","moves":7}},{"2022-11-16T08:44:18.432Z":{"minutes":"00","seconds":"10","moves":9}},{"2022-11-16T08:43:00.198Z":{"minutes":"00","seconds":"10","moves":8}},{"2022-11-16T08:34:48.217Z":{"minutes":"00","seconds":"05","moves":5}}]